README.md
setup.py
shisell/__init__.py
shisell/analytics_context.py
shisell/analytics_dispatcher.py
shisell/analytics_event_model.py
shisell/create_root_dispatcher.py
shisell.egg-info/PKG-INFO
shisell.egg-info/SOURCES.txt
shisell.egg-info/dependency_links.txt
shisell.egg-info/top_level.txt
shisell/extenders/__init__.py
shisell/extenders/create_scoped.py
shisell/extenders/with_context.py
shisell/extenders/with_extras.py
shisell/extenders/with_filter.py
shisell/extenders/with_identities.py
shisell/extenders/with_meta.py
shisell/filters/__init__.py
shisell/filters/time_filter.py
shisell/writers/__init__.py
shisell/writers/log_writer.py