Metadata-Version: 2.1
Name: shisell
Version: 1.0.0
Summary: Shisell is a service agnostic abstraction for analytic dispatchers.
Home-page: https://github.com/Soluto/shisell-python
Author: Soluto
Author-email: it@soluto.com
License: MIT
Platform: UNKNOWN
Classifier: License :: OSI Approved :: MIT License
Classifier: Operating System :: OS Independent
Classifier: Programming Language :: Python :: 3
